nso_jsonrpc_requester/__init__.py
nso_jsonrpc_requester/comet.py
nso_jsonrpc_requester/common.py
nso_jsonrpc_requester/config.py
nso_jsonrpc_requester/version.py
nso_jsonrpc_requester-1.1.0.dist-info/LICENSE
nso_jsonrpc_requester-1.1.0.dist-info/METADATA
nso_jsonrpc_requester-1.1.0.dist-info/WHEEL
nso_jsonrpc_requester-1.1.0.dist-info/top_level.txt
nso_jsonrpc_requester-1.1.0.dist-info/RECORD
