Metadata-Version: 2.1
Name: nso-jsonrpc-requester
Version: 1.1.0
Summary: A simple logger that logs in a JSON format inspired by go zap
Author-email: "Benjamin P. Trachtenberg" <e_ben_75-python@yahoo.com>
Maintainer-email: "Benjamin P. Trachtenberg" <e_ben_75-python@yahoo.com>
License: MIT License
Project-URL: Documentation, https://nso-jsonrpc-requester.readthedocs.io/en/latest
Project-URL: Source, https://github.com/btr1975/nso_jsonrpc_requester
Project-URL: Tracker, https://github.com/btr1975/nso_jsonrpc_requester/issues
Keywords: cisco,nso,json,rpc,network,engineer
Classifier: Development Status :: 5 - Production/Stable
Classifier: License :: OSI Approved :: MIT License
Classifier: Intended Audience :: Developers
Classifier: Natural Language :: English
Classifier: Operating System :: MacOS :: MacOS X
Classifier: Operating System :: POSIX
Classifier: Operating System :: POSIX :: BSD
Classifier: Operating System :: POSIX :: Linux
Classifier: Operating System :: Microsoft :: Windows
Classifier: Programming Language :: Python :: 3
Classifier: Programming Language :: Python :: 3 :: Only
Classifier: Programming Language :: Python :: 3.8
Classifier: Programming Language :: Python :: 3.9
Classifier: Programming Language :: Python :: 3.10
Classifier: Programming Language :: Python :: 3.11
Requires-Python: >=3.8
License-File: LICENSE
Requires-Dist: requests (~=2.28.2)
Requires-Dist: PyYAML (~=6.0)
